{"signs":[{"x":-1547,"y":120,"z":-1329,"type":"sign","kind":"sign","material":"mangrove","front_text":[[{"text":"Map: Seaside","color":"black"}],[{"text":"plateau, nearby","color":"black"}],[{"text":"village","color":"black"}],[{"text":"","color":"black"}]]},{"x":-909,"y":166,"z":-1627,"type":"sign","kind":"sign","material":"mangrove","front_text":[[{"text":"Map: lonely","color":"black"}],[{"text":"mountain, cherry","color":"black"}],[{"text":"trees","color":"black"}],[{"text":"","color":"black"}]]},{"x":-421,"y":112,"z":-1585,"type":"sign","kind":"sign","material":"mangrove","front_text":[[{"text":"Map: Hilltop","color":"black"}],[{"text":"Overlook river,","color":"black"}],[{"text":"forest, mountains","color":"black"}],[{"text":"","color":"black"}]]},{"x":-4097,"y":111,"z":4502,"type":"sign","kind":"sign","material":"mangrove","front_text":[[{"text":"Map: Terracotta","color":"black"}],[{"text":"overlook desert","color":"black"}],[{"text":"","color":"black"}],[{"text":"","color":"black"}]]},{"x":-2640,"y":124,"z":62,"type":"sign","kind":"sign","material":"mangrove","front_text":[[{"text":"Map: Forest cliff","color":"black"}],[{"text":"overlook village","color":"black"}],[{"text":"delved too deep","color":"black"}],[{"text":"","color":"black"}]]},{"x":-2521,"y":128,"z":1007,"type":"sign","kind":"sign","material":"mangrove","front_text":[[{"text":"Map: Inactive","color":"black"}],[{"text":"volcano caldera","color":"black"}],[{"text":"","color":"black"}],[{"text":"","color":"black"}]]},{"x":-2687,"y":119,"z":1242,"type":"sign","kind":"sign","material":"mangrove","front_text":[[{"text":"Map: Scenic cliff","color":"black"}],[{"text":"waterfall to ","color":"black"}],[{"text":"large cavern","color":"black"}],[{"text":"","color":"black"}]]},{"x":-3936,"y":131,"z":3089,"type":"sign","kind":"sign","material":"mangrove","front_text":[[{"text":"Map: Big plateau","color":"black"}],[{"text":"cavern below","color":"black"}],[{"text":"","color":"black"}],[{"text":"","color":"black"}]]},{"x":-2226,"y":114,"z":3706,"type":"sign","kind":"sign","material":"mangrove","front_text":[[{"text":"Map: Big plateau","color":"black"}],[{"text":"","color":"black"}],[{"text":"","color":"black"}],[{"text":"","color":"black"}]]},{"x":-3963,"y":77,"z":4607,"type":"sign","kind":"sign","material":"mangrove","front_text":[[{"text":"Map: Flat-bottom","color":"black"}],[{"text":"cavern","color":"black"}],[{"text":"","color":"black"}],[{"text":"","color":"black"}]]},{"x":-3175,"y":200,"z":4268,"type":"sign","kind":"sign","material":"mangrove","front_text":[[{"text":"Map: Mountain","color":"black"}],[{"text":"plateau","color":"black"}],[{"text":"","color":"black"}],[{"text":"","color":"black"}]]},{"x":-2762,"y":22,"z":4548,"type":"sign","kind":"sign","material":"mangrove","front_text":[[{"text":"Map: Deep sun,","color":"black"}],[{"text":"massive pillars","color":"black"}],[{"text":"","color":"black"}],[{"text":"","color":"black"}]]},{"x":-2550,"y":131,"z":4655,"type":"sign","kind":"sign","material":"mangrove","front_text":[[{"text":"Map: Lava door","color":"black"}],[{"text":"high mountain","color":"black"}],[{"text":"valley","color":"black"}],[{"text":"","color":"black"}]]},{"x":-1113,"y":179,"z":4334,"type":"sign","kind":"sign","material":"mangrove","front_text":[[{"text":"Map: Floating","color":"black"}],[{"text":"cliff, multi","color":"black"}],[{"text":"level","color":"black"}],[{"text":"","color":"black"}]]},{"x":2612,"y":122,"z":-3273,"type":"sign","kind":"sign","material":"mangrove","front_text":[[{"text":"Map: Ice plateau","color":"black"}],[{"text":"","color":"black"}],[{"text":"","color":"black"}],[{"text":"","color":"black"}]]},{"x":3912,"y":147,"z":-3188,"type":"sign","kind":"sign","material":"mangrove","front_text":[[{"text":"Map: Small, flat-","color":"black"}],[{"text":"topped mountain","color":"black"}],[{"text":"","color":"black"}],[{"text":"","color":"black"}]]},{"x":3674,"y":112,"z":-3008,"type":"sign","kind":"sign","material":"mangrove","front_text":[[{"text":"Map: Meadow","color":"black"}],[{"text":"plateau","color":"black"}],[{"text":"","color":"black"}],[{"text":"","color":"black"}]]},{"x":3620,"y":143,"z":-113,"type":"sign","kind":"sign","material":"mangrove","front_text":[[{"text":"Map: Plateau","color":"black"}],[{"text":"Private reef dive","color":"black"}],[{"text":"","color":"black"}],[{"text":"","color":"black"}]]},{"x":4210,"y":120,"z":-4054,"type":"sign","kind":"sign","material":"mangrove","front_text":[[{"text":"Map: Big meadow","color":"black"}],[{"text":"plateau","color":"black"}],[{"text":"","color":"black"}],[{"text":"","color":"black"}]]},{"x":4503,"y":95,"z":-2125,"type":"sign","kind":"sign","material":"mangrove","front_text":[[{"text":"Map: Island","color":"black"}],[{"text":"plateau","color":"black"}],[{"text":"","color":"black"}],[{"text":"","color":"black"}]]},{"x":4580,"y":120,"z":-2370,"type":"sign","kind":"sign","material":"mangrove","front_text":[[{"text":"Map: Sandstone","color":"black"}],[{"text":"cliffs","color":"black"}],[{"text":"","color":"black"}],[{"text":"","color":"black"}]]},{"x":1252,"y":130,"z":3317,"type":"sign","kind":"sign","material":"mangrove","front_text":[[{"text":"Map: Cherry","color":"black"}],[{"text":"plateau","color":"black"}],[{"text":"","color":"black"}],[{"text":"","color":"black"}]]},{"x":2496,"y":164,"z":107,"type":"sign","kind":"sign","material":"mangrove","front_text":[[{"text":"Map: Massive","color":"black"}],[{"text":"plateau","color":"black"}],[{"text":"","color":"black"}],[{"text":"","color":"black"}]]},{"x":2333,"y":104,"z":962,"type":"sign","kind":"sign","material":"mangrove","front_text":[[{"text":"Map: Teracotta","color":"black"}],[{"text":"canyon overlook","color":"black"}],[{"text":"","color":"black"}],[{"text":"","color":"black"}]]},{"x":719,"y":112,"z":5552,"type":"sign","kind":"sign","material":"mangrove","front_text":[[{"text":"Map: Plateau","color":"black"}],[{"text":"meadow","color":"black"}],[{"text":"","color":"black"}],[{"text":"","color":"black"}]]},{"x":974,"y":63,"z":5611,"type":"sign","kind":"sign","material":"mangrove","front_text":[[{"text":"Map: Pirate cove","color":"black"}],[{"text":"","color":"black"}],[{"text":"","color":"black"}],[{"text":"","color":"black"}]]},{"x":3650,"y":110,"z":4152,"type":"sign","kind":"sign","material":"mangrove","front_text":[[{"text":"Map: River loop","color":"black"}],[{"text":"plateau","color":"black"}],[{"text":"","color":"black"}],[{"text":"","color":"black"}]]},{"x":3312,"y":120,"z":5465,"type":"sign","kind":"sign","material":"mangrove","front_text":[[{"text":"Map: Meadow","color":"black"}],[{"text":"plateau, dual lake","color":"black"}],[{"text":"overlook","color":"black"}],[{"text":"","color":"black"}]]}]}